KFinanceDataReader/KFinanceDataReader.py
KFinanceDataReader/__init__.py
KFinanceDataReader/_corp_data_reader.py
KFinanceDataReader/_macro_data_reader.py
KFinanceDataReader/_market_data_reader.py
KFinanceDataReader/DartDataReader/__init__.py
KFinanceDataReader/DartDataReader/fetcher.py
KFinanceDataReader/DartDataReader/reader.py
KFinanceDataReader/DartDataReader/utils.py
KFinanceDataReader/DartDataReader/data_reader/__init__.py
KFinanceDataReader/DartDataReader/data_reader/corp.py
KFinanceDataReader/DartDataReader/data_reader/fundamental.py
KFinanceDataReader/EcosDataReader/__init__.py
KFinanceDataReader/EcosDataReader/fetcher.py
KFinanceDataReader/EcosDataReader/reader.py
KFinanceDataReader/EcosDataReader/data_reader/__init__.py
KFinanceDataReader/EcosDataReader/data_reader/_data_reader.py
KFinanceDataReader/EcosDataReader/data_reader/bank.py
KFinanceDataReader/EcosDataReader/data_reader/economic_index.py
KFinanceDataReader/EcosDataReader/data_reader/foreign_currency.py
KFinanceDataReader/EcosDataReader/data_reader/global_index.py
KFinanceDataReader/EcosDataReader/data_reader/interest.py
KFinanceDataReader/EcosDataReader/data_reader/market.py
KFinanceDataReader/EcosDataReader/data_reader/monetary.py
KFinanceDataReader/EcosDataReader/data_reader/payment.py
KFinanceDataReader/EcosDataReader/data_reader/price_index.py
KFinanceDataReader/EcosDataReader/data_reader/trade.py
KFinanceDataReader/KrxDataReader/__init__.py
KFinanceDataReader/KrxDataReader/fetcher.py
KFinanceDataReader/KrxDataReader/reader.py
KFinanceDataReader/KrxDataReader/data_reader/__init__.py
KFinanceDataReader/KrxDataReader/data_reader/base.py
KFinanceDataReader/KrxDataReader/data_reader/etc.py
KFinanceDataReader/KrxDataReader/data_reader/foreign.py
KFinanceDataReader/KrxDataReader/data_reader/sector.py
KFinanceDataReader/KrxDataReader/data_reader/trader.py
KFinanceDataReader-1.1.0.dist-info/METADATA
KFinanceDataReader-1.1.0.dist-info/WHEEL
KFinanceDataReader-1.1.0.dist-info/top_level.txt
KFinanceDataReader-1.1.0.dist-info/RECORD
