Metadata-Version: 2.1
Name: KFinanceDataReader
Version: 1.1.0
Summary: 한국 주요 금융 데이터 추출을 위한 라이브러리
Home-page: https://github.com/jackmappotion/KFinanceDataReader
Author: jackmappotion
Author-email: jackmappotion@gmail.com
Classifier: Programming Language :: Python :: 3
Classifier: License :: OSI Approved :: MIT License
Classifier: Operating System :: OS Independent
Requires-Python: >=3.7
Requires-Dist: requests >=2.0.0
Requires-Dist: pandas >=2.0.0
Requires-Dist: finance-datareader
Requires-Dist: plotly
Requires-Dist: xmltodict
